bfg_friendly/__init__.py
bfg_friendly/__main__.py
bfg_friendly/cli.py
bfg_friendly/main.py
bfg_friendly/py.typed
bfg_friendly-0.0.13.dist-info/METADATA
bfg_friendly-0.0.13.dist-info/WHEEL
bfg_friendly-0.0.13.dist-info/entry_points.txt
bfg_friendly-0.0.13.dist-info/licenses/LICENSE
bfg_friendly-0.0.13.dist-info/RECORD
