Metadata-Version: 2.4
Name: bfg-friendly
Version: 0.0.13
Summary: Friendly CLI tool for removing sensitive data from a repository 
License: MIT
License-File: LICENSE
Author: 34j
Author-email: 34j.95a2p@simplelogin.com
Requires-Python: >=3.8,<4.0
Classifier: Development Status :: 2 - Pre-Alpha
Classifier: Intended Audience :: Developers
Classifier: License :: OSI Approved :: MIT License
Classifier: Natural Language :: English
Classifier: Operating System :: OS Independent
Classifier: Programming Language :: Python :: 3
Classifier: Programming Language :: Python :: 3.8
Classifier: Programming Language :: Python :: 3.9
Classifier: Programming Language :: Python :: 3.10
Classifier: Programming Language :: Python :: 3.11
Classifier: Programming Language :: Python :: 3.12
Classifier: Programming Language :: Python :: 3.13
Classifier: Programming Language :: Python :: 3.14
Classifier: Topic :: Software Development :: Libraries
Requires-Dist: rich (>=10)
Requires-Dist: typer[all] (>=0.20.0,<0.21.0)
Project-URL: Bug Tracker, https://github.com/34j/bfg-friendly/issues
Project-URL: Changelog, https://github.com/34j/bfg-friendly/blob/main/CHANGELOG.md
Project-URL: Documentation, https://bfg-friendly.readthedocs.io
Project-URL: Repository, https://github.com/34j/bfg-friendly
